gh_pre/__init__.py
gh_pre/__main__.py
gh_pre-0.1.0.dist-info/LICENSE.txt
gh_pre-0.1.0.dist-info/METADATA
gh_pre-0.1.0.dist-info/WHEEL
gh_pre-0.1.0.dist-info/entry_points.txt
gh_pre-0.1.0.dist-info/top_level.txt
gh_pre-0.1.0.dist-info/RECORD
